battle_box_client/__init__.py
battle_box_client/client.py
battle_box_client/examples.py
battle_box_client-0.0.2.dist-info/LICENSE
battle_box_client-0.0.2.dist-info/METADATA
battle_box_client-0.0.2.dist-info/WHEEL
battle_box_client-0.0.2.dist-info/top_level.txt
battle_box_client-0.0.2.dist-info/RECORD
