Metadata-Version: 2.1
Name: battle-box-client
Version: 0.0.2
Summary: Battle Box Client
Home-page: https://github.com/FlyingDutchmanGames/battle_box_client_py
Author: Grant Powell
License: UNKNOWN
Platform: UNKNOWN
Classifier: Programming Language :: Python :: 3
Classifier: License :: OSI Approved :: Apache Software License
Classifier: Operating System :: OS Independent
Requires-Python: >=3.6
